riguima_calculator_cli/__init__.py
riguima_calculator_cli/main.py
riguima_calculator_cli-0.1.1.dist-info/METADATA
riguima_calculator_cli-0.1.1.dist-info/WHEEL
riguima_calculator_cli-0.1.1.dist-info/entry_points.txt
riguima_calculator_cli-0.1.1.dist-info/RECORD
