Metadata-Version: 2.1
Name: riguima-calculator-cli
Version: 0.1.1
Summary: Calculator CLI made from app ideas repo: https://github.com/florinpop17/app-ideas
Author: Richard
Author-email: richard.alexsander.guima@gmail.com
Requires-Python: >=3.11,<4.0
Classifier: Programming Language :: Python :: 3
Classifier: Programming Language :: Python :: 3.11
Requires-Dist: click (>=8.1.7,<9.0.0)
